examplesky/__init__.py
examplesky-4.0.dist-info/METADATA
examplesky-4.0.dist-info/WHEEL
examplesky-4.0.dist-info/RECORD
