Metadata-Version: 2.4
Name: examplesky
Version: 4.0
Summary: An example Python package for use in a PyTexas 2025 tutorial by Al Sweigart.
Author-email: Al Sweigart <al@inventwithpython.com>
